xPDF50/__init__.py
xPDF50/__main__.py
xPDF50-1.0.7.dist-info/LICENSE.txt
xPDF50-1.0.7.dist-info/METADATA
xPDF50-1.0.7.dist-info/WHEEL
xPDF50-1.0.7.dist-info/entry_points.txt
xPDF50-1.0.7.dist-info/top_level.txt
xPDF50-1.0.7.dist-info/RECORD
