Metadata-Version: 2.1
Name: xPDF50
Version: 1.0.7
Summary: Downloads clean PDFs of CS50 course materials from cs50.harvard.edu web pages
Home-page: https://github.com/thaare87/projects/tree/master/xPDF50
Author: Thaare87
Author-email: thaare87@gmail.com
Classifier: Programming Language :: Python :: 3.6
Classifier: Programming Language :: Python :: 3.7
Classifier: License :: OSI Approved :: MIT License
Classifier: Operating System :: OS Independent
Requires-Python: >=3.6
License-File: LICENSE.txt
Provides-Extra: dev
Requires-Dist: pytest (>=3.7) ; extra == 'dev'
